finance_report/__init__.py
finance_report/cli.py
finance_report/report_generator.py
finance_report-0.1.6.dist-info/METADATA
finance_report-0.1.6.dist-info/WHEEL
finance_report-0.1.6.dist-info/entry_points.txt
finance_report-0.1.6.dist-info/top_level.txt
finance_report-0.1.6.dist-info/RECORD
